fdby_stt/__init__.py
fdby_stt-0.1.1.dist-info/METADATA
fdby_stt-0.1.1.dist-info/WHEEL
fdby_stt-0.1.1.dist-info/top_level.txt
fdby_stt-0.1.1.dist-info/RECORD
