Metadata-Version: 2.1
Name: fdby-stt
Version: 0.1.1
Summary: this is a speech to text package created by Sachin Gadwal
Author: Sachin Gadwal
Author-email: sachingadwal1899@gmail.com
Requires-Dist: selenium
Requires-Dist: webdriver-manager
